{"cameraMode":{"drawMode":0,"name":"Shaded","section":"Shading Mode"},"sceneLighting":false,"audioPlay":false,"sceneViewState":{"showFog":true,"showMaterialUpdate":false,"showSkybox":false,"showFlares":true,"showImageEffects":true,"showParticleSystems":true},"in2DMode":false,"pivot":{"x":0.08862321823835373,"y":-0.3344704806804657,"z":0.10946536809206009},"rotation":{"x":-0.24817465245723725,"y":0.012205881997942925,"z":-0.0031145948451012375,"w":-0.9686601161956787},"size":1.0437865257263184,"orthographic":false}